src/CU.v
module CU(
input clk,
input start,
input equals,
input regBk,
output LoadA,
output LoadCoun,
output LoadB,
output ShiftB,
output LoadC,
output S_Coun,
output [1:0] S_C,
output reg Done
);
parameter   STEP1 = 3'b001,
            STEP2 = 3'b010,
            STEP3 = 3'b011,
            STEP4 = 3'b100,
            STEP5 = 3'b101;

reg [2:0] state = STEP1;

reg [7:0] control_word;
assign {LoadA, LoadCoun, LoadB, ShiftB, LoadC, S_Coun, S_C} = control_word;
always@(posedge clk) begin 
        case(state)
            STEP1: begin 
                Done <= 0;
                if(!start) begin
                    control_word <= 8'b00001000;
                    state <= STEP1;
                end else begin
                    control_word <= 8'b11101000;
                    state <= STEP2;
                end
            end
            STEP2: 
                if(!equals) begin
                    control_word <= 8'b01001101;
                    state <= STEP3;
                end else begin
                    control_word <= 8'b01000100;
                    state <= STEP1; 
                    Done <= 1;
                end
            
            STEP3: begin
                control_word <= 8'b00000000;
                state <= STEP4;
            end
            STEP4:
                if(!regBk) begin
                    control_word <= 8'b00010000;
                    state <= STEP2;
                end else begin
                    control_word <= 8'b00011010;
                    state <= STEP5;
                end
            STEP5: begin
                control_word <= 8'b00000000;
                state <= STEP2;
            end
        endcase
    end


endmodule

tb/CU_tb.v
module CU_tb();
reg clk;
reg start;
reg equals;
reg regBk;
wire LoadA;
wire LoadCoun;
wire LoadB;
wire ShiftB;
wire LoadC;
wire S_Coun;
wire [1:0] S_C;

    always begin
        #5 clk = ~clk;
    end

CU CU_inst(
    .clk(clk),
    .start(start),
    .equals(equals),
    .regBk(regBk),
    .LoadA(LoadA),
    .LoadCoun(LoadCoun),
    .LoadB(LoadB),
    .ShiftB(ShiftB),
    .LoadC(LoadC),
    .S_Coun(S_Coun),
    .S_C(S_C)
);

initial begin
    $dumpfile("CU_tb.vcd");
    $dumpvars(0, CU_tb);
    clk = 1;
    start = 0;
    equals = 0;
    regBk = 0;
    //Step 1 to Step 2
    #20 start = 1;

    //Step 2 to Step 3
    #10 equals = 0;

    //Step 2 to Step 1
    #10 equals = 1;
    //Step 3 to Step 4 
    //has no condition

    //Step 4 to Step 5
    #10 regBk = 1;

    //Step 5 to Step 2 
    //has no condition

    //Step 2 to Step 3
    #10 equals = 0;

    #10 regBk = 0;
    #10 start = 1;
    #10 equals = 1;
    #10 start = 0;
    #10 equals = 0;
    $finish;
end

endmodule

res/waveform/CU_tb.vcd
$date
	Sun Apr 16 20:49:05 2023
$end
$version
	Icarus Verilog
$end
$timescale
	1s
$end
$scope module CU_tb $end
$var wire 1 ! ShiftB $end
$var wire 1 " S_Coun $end
$var wire 2 # S_C [1:0] $end
$var wire 1 $ LoadCoun $end
$var wire 1 % LoadC $end
$var wire 1 & LoadB $end
$var wire 1 ' LoadA $end
$var reg 1 ( clk $end
$var reg 1 ) equals $end
$var reg 1 * regBk $end
$var reg 1 + start $end
$scope module CU_inst $end
$var wire 1 ( clk $end
$var wire 1 ) equals $end
$var wire 1 * regBk $end
$var wire 1 + start $end
$var wire 1 ! ShiftB $end
$var wire 1 " S_Coun $end
$var wire 2 , S_C [1:0] $end
$var wire 1 $ LoadCoun $end
$var wire 1 % LoadC $end
$var wire 1 & LoadB $end
$var wire 1 ' LoadA $end
$var parameter 3 - STEP1 $end
$var parameter 3 . STEP2 $end
$var parameter 3 / STEP3 $end
$var parameter 3 0 STEP4 $end
$var parameter 3 1 STEP5 $end
$var reg 1 2 Done $end
$var reg 8 3 control_word [7:0] $end
$var reg 3 4 state [2:0] $end
$upscope $end
$upscope $end
$enddefinitions $end
$comment Show the parameter values. $end
$dumpall
b101 1
b100 0
b11 /
b10 .
b1 -
$end
#0
$dumpvars
b1 4
b1000 3
02
b0 ,
0+
0*
0)
1(
0'
0&
1%
0$
b0 #
0"
0!
$end
#5
0(
#10
1(
#15
0(
#20
1'
1$
1&
b10 4
b11101000 3
1(
1+
#25
0(
#30
0'
0&
1"
b1 #
b1 ,
b11 4
b1001101 3
1(
#35
0(
#40
0$
0%
0"
b0 #
b0 ,
b100 4
b0 3
1(
1)
#45
0(
#50
1!
1%
b10 #
b10 ,
b101 4
b11010 3
1(
1*
#55
0(
#60
0!
0%
b0 #
b0 ,
b10 4
b0 3
1(
0)
#65
0(
#70
1$
1%
1"
b1 #
b1 ,
b11 4
b1001101 3
1(
0*
#75
0(
#80
0$
0%
0"
b0 #
b0 ,
b100 4
b0 3
1(
#85
0(
#90
1!
b10 4
b10000 3
1(
1)
#95
0(
#100
1$
0!
1"
12
b1 4
b1000100 3
1(
0+
#105
0(
#110
0$
1%
0"
b1000 3
02
1(
0)
